{
  "aliases": {},
  "claims": {
    "P39": [
      {
        "id": "Q95323$0E21620E-109A-4B9D-AF9B-557B5A98EBFD",
        "mainsnak": {
          "datatype": "wikibase-item",
          "datavalue": {
            "type": "wikibase-entityid",
            "value": {
              "entity-type": "item",
              "id": "Q153801",
              "numeric-id": 153801
            }
          },
          "hash": "b90991d245ed2a6e8cec5d5ae903ed799cdc2705",
          "property": "P39",
          "snaktype": "value"
        },
        "rank": "normal",
        "type": "statement"
      },
      {
        "id": "Q95323$247D667A-ABF9-47B1-9570-A6A1F8169AA4",
        "mainsnak": {
          "datatype": "wikibase-item",
          "datavalue": {
            "type": "wikibase-entityid",
            "value": {
              "entity-type": "item",
              "id": "Q153802",
              "numeric-id": 153802
            }
          },
          "hash": "b9eb3a19c3f2fb9d80823c0663c5704bf3f90255",
          "property": "P39",
          "snaktype": "value"
        },
        "rank": "normal",
        "type": "statement"
      }
    ],
    "P47": [
      {
        "id": "Q95323$2A09739E-EED9-425C-A1E7-651B72435B9A",
        "mainsnak": {
          "datatype": "wikibase-item",
          "datavalue": {
            "type": "wikibase-entityid",
            "value": {
              "entity-type": "item",
              "id": "Q94934",
              "numeric-id": 94934
            }
          },
          "hash": "19f0ae11855922169424d628ee41dda08b38a5d3",
          "property": "P47",
          "snaktype": "value"
        },
        "rank": "normal",
        "type": "statement"
      }
    ],
    "P55": [
      {
        "id": "Q95323$12DE84D9-3800-498E-96B2-3598B09CBFBF",
        "mainsnak": {
          "datatype": "wikibase-item",
          "datavalue": {
            "type": "wikibase-entityid",
            "value": {
              "entity-type": "item",
              "id": "Q153718",
              "numeric-id": 153718
            }
          },
          "hash": "2c0169b343dfa052299eaa3878c187394e4e584c",
          "property": "P55",
          "snaktype": "value"
        },
        "rank": "normal",
        "type": "statement"
      }
    ],
    "P62": [
      {
        "id": "Q95323$490B5DD7-0A39-45AC-BE2B-DE62CF529B3F",
        "mainsnak": {
          "datatype": "external-id",
          "datavalue": {
            "type": "string",
            "value": "6000000049963231805"
          },
          "hash": "bcbfd035c2504e1e79ff4021037596dd581ed231",
          "property": "P62",
          "snaktype": "value"
        },
        "rank": "normal",
        "type": "statement"
      }
    ]
  },
  "descriptions": {},
  "id": "Q95323",
  "labels": {
    "en": {
      "language": "en",
      "value": "Qassim bin  'Abdallah"
    }
  },
  "lastrevid": 17510095,
  "modified": "2025-09-17T00:23:10Z",
  "ns": 860,
  "pageid": 111270,
  "sitelinks": {},
  "title": "Item:Q95323",
  "type": "item"
}
