{
  "aliases": {
    "en": [
      {
        "language": "en",
        "value": "Midas"
      }
    ]
  },
  "claims": {
    "P20": [
      {
        "id": "Q133749$B4E0A555-EC8D-4F31-9E65-F3C927945F2F",
        "mainsnak": {
          "datatype": "wikibase-item",
          "datavalue": {
            "type": "wikibase-entityid",
            "value": {
              "entity-type": "item",
              "id": "Q134694",
              "numeric-id": 134694
            }
          },
          "hash": "4649b7c63cc4c3f7b4ba6cf9045abac94af06224",
          "property": "P20",
          "snaktype": "value"
        },
        "rank": "normal",
        "type": "statement"
      },
      {
        "id": "Q133749$7955140C-91DC-4EFE-89B7-D345658C00E0",
        "mainsnak": {
          "datatype": "wikibase-item",
          "datavalue": {
            "type": "wikibase-entityid",
            "value": {
              "entity-type": "item",
              "id": "Q134423",
              "numeric-id": 134423
            }
          },
          "hash": "c426d1614e34fdc73bbb16c363ce1aaaa5e27685",
          "property": "P20",
          "snaktype": "value"
        },
        "rank": "normal",
        "type": "statement"
      },
      {
        "id": "Q133749$22DBEDAF-F8FC-4FA4-9694-1EEC706307E3",
        "mainsnak": {
          "datatype": "wikibase-item",
          "datavalue": {
            "type": "wikibase-entityid",
            "value": {
              "entity-type": "item",
              "id": "Q134421",
              "numeric-id": 134421
            }
          },
          "hash": "848eb7951fcc8401758d4d38f55f3755266f64c9",
          "property": "P20",
          "snaktype": "value"
        },
        "rank": "normal",
        "type": "statement"
      },
      {
        "id": "Q133749$9B4F2FD4-EE25-468E-BB7D-696D1DA93E10",
        "mainsnak": {
          "datatype": "wikibase-item",
          "datavalue": {
            "type": "wikibase-entityid",
            "value": {
              "entity-type": "item",
              "id": "Q134422",
              "numeric-id": 134422
            }
          },
          "hash": "d10e86f7474254d4da3310aec09a91e2c33efef4",
          "property": "P20",
          "snaktype": "value"
        },
        "rank": "normal",
        "type": "statement"
      }
    ],
    "P39": [
      {
        "id": "Q133749$09733731-67CF-452D-82E5-2FC7EAE46778",
        "mainsnak": {
          "datatype": "wikibase-item",
          "datavalue": {
            "type": "wikibase-entityid",
            "value": {
              "entity-type": "item",
              "id": "Q153801",
              "numeric-id": 153801
            }
          },
          "hash": "b90991d245ed2a6e8cec5d5ae903ed799cdc2705",
          "property": "P39",
          "snaktype": "value"
        },
        "rank": "normal",
        "type": "statement"
      },
      {
        "id": "Q133749$9935CA85-6FE4-4E51-8698-A8C09D51A0A1",
        "mainsnak": {
          "datatype": "wikibase-item",
          "datavalue": {
            "type": "wikibase-entityid",
            "value": {
              "entity-type": "item",
              "id": "Q153802",
              "numeric-id": 153802
            }
          },
          "hash": "b9eb3a19c3f2fb9d80823c0663c5704bf3f90255",
          "property": "P39",
          "snaktype": "value"
        },
        "rank": "normal",
        "type": "statement"
      }
    ],
    "P42": [
      {
        "id": "Q133749$E26BC5BB-56ED-4B3A-B27C-967ECCFE7CB4",
        "mainsnak": {
          "datatype": "wikibase-item",
          "datavalue": {
            "type": "wikibase-entityid",
            "value": {
              "entity-type": "item",
              "id": "Q134420",
              "numeric-id": 134420
            }
          },
          "hash": "8668d55597d713d1fd7cc93ae167b7fac81f8b1b",
          "property": "P42",
          "snaktype": "value"
        },
        "rank": "normal",
        "type": "statement"
      }
    ],
    "P47": [
      {
        "id": "Q133749$702E1DBB-527A-4DE3-9842-001761618259",
        "mainsnak": {
          "datatype": "wikibase-item",
          "datavalue": {
            "type": "wikibase-entityid",
            "value": {
              "entity-type": "item",
              "id": "Q134419",
              "numeric-id": 134419
            }
          },
          "hash": "431a0c5bdb60262d2f34a17308678f1266370054",
          "property": "P47",
          "snaktype": "value"
        },
        "rank": "normal",
        "type": "statement"
      }
    ],
    "P48": [
      {
        "id": "Q133749$79B7AA6C-5D09-4247-B690-B3C239BCC584",
        "mainsnak": {
          "datatype": "wikibase-item",
          "datavalue": {
            "type": "wikibase-entityid",
            "value": {
              "entity-type": "item",
              "id": "Q132355",
              "numeric-id": 132355
            }
          },
          "hash": "31369b3077b4692bb9e2e133f4143e8a0423c96f",
          "property": "P48",
          "snaktype": "value"
        },
        "rank": "normal",
        "type": "statement"
      }
    ],
    "P55": [
      {
        "id": "Q133749$C40CCA90-C54F-4DCB-A222-673F45751706",
        "mainsnak": {
          "datatype": "wikibase-item",
          "datavalue": {
            "type": "wikibase-entityid",
            "value": {
              "entity-type": "item",
              "id": "Q153718",
              "numeric-id": 153718
            }
          },
          "hash": "2c0169b343dfa052299eaa3878c187394e4e584c",
          "property": "P55",
          "snaktype": "value"
        },
        "rank": "normal",
        "type": "statement"
      }
    ],
    "P61": [
      {
        "id": "Q133749$0D5BBAB3-9AEA-4F21-ABBC-62CC32031384",
        "mainsnak": {
          "datatype": "external-id",
          "datavalue": {
            "type": "string",
            "value": "Q308398"
          },
          "hash": "7630f905233fc4bc35111328ae4e712a47c7c495",
          "property": "P61",
          "snaktype": "value"
        },
        "rank": "normal",
        "type": "statement"
      }
    ],
    "P94": [
      {
        "id": "Q133749$6E1BC859-43B4-45F4-9E29-3488B254A55D",
        "mainsnak": {
          "datatype": "commonsMedia",
          "datavalue": {
            "type": "string",
            "value": "Midas Arms.svg"
          },
          "hash": "887df5a0203d428766eeed0fde33a0caa83c5bb5",
          "property": "P94",
          "snaktype": "value"
        },
        "rank": "normal",
        "type": "statement"
      }
    ]
  },
  "descriptions": {
    "be-tarask": {
      "language": "be-tarask",
      "value": "герой старажытнагрэцкай міталёгіі"
    },
    "cs": {
      "language": "cs",
      "value": "jméno několika panovníků Frýgie"
    },
    "da": {
      "language": "da",
      "value": "figur i den græske mytologi"
    },
    "de": {
      "language": "de",
      "value": "Person der griechischen Mythologie"
    },
    "en": {
      "language": "en",
      "value": "king with the power to turn whatever he touches to gold"
    },
    "es": {
      "language": "es",
      "value": "rey de Frigia"
    },
    "eu": {
      "language": "eu",
      "value": "Frigiako erregea, ikutzen zuen guztia urre bihurtzeko dohaina zeukana"
    },
    "fa": {
      "language": "fa",
      "value": "پادشاه افسانه ای یونان که با لمس اشیا انها را به طلا تبدیل میکرد"
    },
    "fi": {
      "language": "fi",
      "value": "Fryygian kuningas"
    },
    "fr": {
      "language": "fr",
      "value": "roi de Phrygie et personnage de la mythologie gréco-romaine"
    },
    "he": {
      "language": "he",
      "value": "דמות מהמיתולוגיה היוונית"
    },
    "hu": {
      "language": "hu",
      "value": "görög mitológiai alak"
    },
    "id": {
      "language": "id",
      "value": "Raja"
    },
    "it": {
      "language": "it",
      "value": "re mitologico della Frigia"
    },
    "ja": {
      "language": "ja",
      "value": "ギリシャ神話に登場する触れた物を黄金に変える力を持った王"
    },
    "ko": {
      "language": "ko",
      "value": "그리스 신화에 등장하는 만지는 것을 모두 금으로 만드는 왕"
    },
    "nl": {
      "language": "nl",
      "value": "mythologie"
    },
    "ro": {
      "language": "ro",
      "value": "rege mitologic grec"
    },
    "ru": {
      "language": "ru",
      "value": "персонаж древнегреческой мифологии"
    },
    "sv": {
      "language": "sv",
      "value": "frygisk kung, verklig och mytisk"
    },
    "ta": {
      "language": "ta",
      "value": "தொட்டதெல்லாம் பொன்னாகும் வரம்பெற்ற அரசன்"
    },
    "tr": {
      "language": "tr",
      "value": "Frigya Kralı"
    },
    "vi": {
      "language": "vi",
      "value": "vị vua với sức mạnh biến mọi thứ ông chạm vào thành vàng"
    },
    "yue": {
      "language": "yue",
      "value": "希臘神話入面嘅一個國王，佢有能力將任何佢掂到嘅嘢變成金。"
    }
  },
  "id": "Q133749",
  "labels": {
    "af": {
      "language": "af",
      "value": "Midas"
    },
    "ar": {
      "language": "ar",
      "value": "ميداس"
    },
    "arz": {
      "language": "arz",
      "value": "ميداس"
    },
    "az": {
      "language": "az",
      "value": "Midas"
    },
    "be": {
      "language": "be",
      "value": "Мідас"
    },
    "be-tarask": {
      "language": "be-tarask",
      "value": "Мідас"
    },
    "bg": {
      "language": "bg",
      "value": "Мидас"
    },
    "bn": {
      "language": "bn",
      "value": "মিডাস"
    },
    "br": {
      "language": "br",
      "value": "Midas"
    },
    "ca": {
      "language": "ca",
      "value": "Mides I"
    },
    "cs": {
      "language": "cs",
      "value": "Midas"
    },
    "cy": {
      "language": "cy",
      "value": "Midas"
    },
    "da": {
      "language": "da",
      "value": "Midas"
    },
    "de": {
      "language": "de",
      "value": "Midas"
    },
    "el": {
      "language": "el",
      "value": "Μίδας"
    },
    "en": {
      "language": "en",
      "value": "Midas"
    },
    "en-ca": {
      "language": "en-ca",
      "value": "Midas"
    },
    "en-gb": {
      "language": "en-gb",
      "value": "Midas"
    },
    "eo": {
      "language": "eo",
      "value": "Midaso"
    },
    "es": {
      "language": "es",
      "value": "Midas"
    },
    "eu": {
      "language": "eu",
      "value": "Midas"
    },
    "fa": {
      "language": "fa",
      "value": "میداس"
    },
    "fi": {
      "language": "fi",
      "value": "Midas"
    },
    "fr": {
      "language": "fr",
      "value": "Midas"
    },
    "gl": {
      "language": "gl",
      "value": "Midas"
    },
    "grc": {
      "language": "grc",
      "value": "Μίδας"
    },
    "gu": {
      "language": "gu",
      "value": "મિડાસ"
    },
    "he": {
      "language": "he",
      "value": "מידאס"
    },
    "hu": {
      "language": "hu",
      "value": "Midász"
    },
    "hy": {
      "language": "hy",
      "value": "Միդաս"
    },
    "id": {
      "language": "id",
      "value": "Midas"
    },
    "io": {
      "language": "io",
      "value": "Midas"
    },
    "it": {
      "language": "it",
      "value": "Mida"
    },
    "ja": {
      "language": "ja",
      "value": "ミダース"
    },
    "kk": {
      "language": "kk",
      "value": "Мидас"
    },
    "kk-arab": {
      "language": "kk-arab",
      "value": "مىيداس"
    },
    "kk-cn": {
      "language": "kk-cn",
      "value": "مىيداس"
    },
    "kk-cyrl": {
      "language": "kk-cyrl",
      "value": "Мидас"
    },
    "kk-kz": {
      "language": "kk-kz",
      "value": "Мидас"
    },
    "kk-latn": {
      "language": "kk-latn",
      "value": "Mïdas"
    },
    "kk-tr": {
      "language": "kk-tr",
      "value": "Mïdas"
    },
    "ko": {
      "language": "ko",
      "value": "미다스"
    },
    "ku": {
      "language": "ku",
      "value": "Mîdas"
    },
    "ku-latn": {
      "language": "ku-latn",
      "value": "Mìdas"
    },
    "la": {
      "language": "la",
      "value": "Midas"
    },
    "lv": {
      "language": "lv",
      "value": "Midass"
    },
    "mk": {
      "language": "mk",
      "value": "Мида"
    },
    "mr": {
      "language": "mr",
      "value": "राजा मिडास"
    },
    "ms": {
      "language": "ms",
      "value": "Midas"
    },
    "nb": {
      "language": "nb",
      "value": "Midas"
    },
    "nl": {
      "language": "nl",
      "value": "Midas"
    },
    "oc": {
      "language": "oc",
      "value": "Midas"
    },
    "pl": {
      "language": "pl",
      "value": "Midas"
    },
    "pt": {
      "language": "pt",
      "value": "Midas"
    },
    "pt-br": {
      "language": "pt-br",
      "value": "Midas"
    },
    "ro": {
      "language": "ro",
      "value": "Midas"
    },
    "ru": {
      "language": "ru",
      "value": "Мидас"
    },
    "sk": {
      "language": "sk",
      "value": "Midas"
    },
    "sl": {
      "language": "sl",
      "value": "Midas"
    },
    "sq": {
      "language": "sq",
      "value": "Midas"
    },
    "sr": {
      "language": "sr",
      "value": "Мида"
    },
    "sr-ec": {
      "language": "sr-ec",
      "value": "Мида"
    },
    "sr-el": {
      "language": "sr-el",
      "value": "Mida"
    },
    "sv": {
      "language": "sv",
      "value": "Midas"
    },
    "ta": {
      "language": "ta",
      "value": "மிதாசு"
    },
    "th": {
      "language": "th",
      "value": "พระเจ้าไมดาส"
    },
    "tr": {
      "language": "tr",
      "value": "Kral Midas"
    },
    "uk": {
      "language": "uk",
      "value": "Мідас"
    },
    "ur": {
      "language": "ur",
      "value": "میداس"
    },
    "vi": {
      "language": "vi",
      "value": "Midas"
    },
    "yue": {
      "language": "yue",
      "value": "邁達斯"
    },
    "zh": {
      "language": "zh",
      "value": "迈达斯"
    },
    "zh-cn": {
      "language": "zh-cn",
      "value": "迈达斯"
    },
    "zh-hans": {
      "language": "zh-hans",
      "value": "迈达斯"
    },
    "zh-hant": {
      "language": "zh-hant",
      "value": "邁達斯"
    },
    "zh-hk": {
      "language": "zh-hk",
      "value": "邁達斯"
    },
    "zh-sg": {
      "language": "zh-sg",
      "value": "迈达斯"
    },
    "zh-tw": {
      "language": "zh-tw",
      "value": "邁達斯"
    }
  },
  "lastrevid": 17548378,
  "modified": "2025-09-17T09:39:32Z",
  "ns": 860,
  "pageid": 162134,
  "sitelinks": {},
  "title": "Item:Q133749",
  "type": "item"
}
