{
  "aliases": {
    "en": [
      {
        "language": "en",
        "value": "NN (2) ferch William ap Jenkin ap Philip"
      }
    ]
  },
  "claims": {
    "P1819": [
      {
        "id": "Q145899$A7879ACA-BC06-4FDB-91F5-C672DC12E792",
        "mainsnak": {
          "datatype": "external-id",
          "datavalue": {
            "type": "string",
            "value": "I00736687"
          },
          "hash": "cd1a7bf71a0019874ab6f6de7284de5857b67351",
          "property": "P1819",
          "snaktype": "value"
        },
        "rank": "normal",
        "type": "statement"
      }
    ],
    "P20": [
      {
        "id": "Q145899$6CC3C1C0-BF81-4E78-B9D6-F8DB52C9BC82",
        "mainsnak": {
          "datatype": "wikibase-item",
          "datavalue": {
            "type": "wikibase-entityid",
            "value": {
              "entity-type": "item",
              "id": "Q150128",
              "numeric-id": 150128
            }
          },
          "hash": "ef5c4e17352d18873c0bdf3954fc0f17084b07f5",
          "property": "P20",
          "snaktype": "value"
        },
        "rank": "normal",
        "type": "statement"
      }
    ],
    "P39": [
      {
        "id": "Q145899$C34C041C-46AE-407A-A2D9-508FF5596CF4",
        "mainsnak": {
          "datatype": "wikibase-item",
          "datavalue": {
            "type": "wikibase-entityid",
            "value": {
              "entity-type": "item",
              "id": "Q153801",
              "numeric-id": 153801
            }
          },
          "hash": "b90991d245ed2a6e8cec5d5ae903ed799cdc2705",
          "property": "P39",
          "snaktype": "value"
        },
        "rank": "normal",
        "type": "statement"
      },
      {
        "id": "Q145899$3AEB7299-3B0F-4A8E-A0C0-E11DA1F49906",
        "mainsnak": {
          "datatype": "wikibase-item",
          "datavalue": {
            "type": "wikibase-entityid",
            "value": {
              "entity-type": "item",
              "id": "Q153802",
              "numeric-id": 153802
            }
          },
          "hash": "b9eb3a19c3f2fb9d80823c0663c5704bf3f90255",
          "property": "P39",
          "snaktype": "value"
        },
        "rank": "normal",
        "type": "statement"
      }
    ],
    "P42": [
      {
        "id": "Q145899$B7219964-081D-486C-B8AE-E449FCC25581",
        "mainsnak": {
          "datatype": "wikibase-item",
          "datavalue": {
            "type": "wikibase-entityid",
            "value": {
              "entity-type": "item",
              "id": "Q145627",
              "numeric-id": 145627
            }
          },
          "hash": "84f3c9d22f18c71f1dfff52dfa2ee84bc5262d0a",
          "property": "P42",
          "snaktype": "value"
        },
        "rank": "normal",
        "type": "statement"
      }
    ],
    "P47": [
      {
        "id": "Q145899$682EE3F0-1FDF-4E16-939D-BD95C481EFC5",
        "mainsnak": {
          "datatype": "wikibase-item",
          "datavalue": {
            "type": "wikibase-entityid",
            "value": {
              "entity-type": "item",
              "id": "Q142754",
              "numeric-id": 142754
            }
          },
          "hash": "7b18b5a7e2ffd3fbff707c1f0e80dc74323398bd",
          "property": "P47",
          "snaktype": "value"
        },
        "rank": "normal",
        "type": "statement"
      }
    ],
    "P55": [
      {
        "id": "Q145899$5793B0FA-C17E-4275-8BB8-E56AE1670AF5",
        "mainsnak": {
          "datatype": "wikibase-item",
          "datavalue": {
            "type": "wikibase-entityid",
            "value": {
              "entity-type": "item",
              "id": "Q153719",
              "numeric-id": 153719
            }
          },
          "hash": "b13089fc8bec4016f0842734a590d288c2e6ef4b",
          "property": "P55",
          "snaktype": "value"
        },
        "rank": "normal",
        "type": "statement"
      }
    ],
    "P61": [
      {
        "id": "Q145899$E0DBC2EF-38A4-45F7-B832-65F113413EC5",
        "mainsnak": {
          "datatype": "external-id",
          "datavalue": {
            "type": "string",
            "value": "Q116146000"
          },
          "hash": "b5d83628dfcdc7b8a657199425b270b13e7a564b",
          "property": "P61",
          "snaktype": "value"
        },
        "rank": "normal",
        "type": "statement"
      }
    ],
    "P94": [
      {
        "id": "Q145899$7224223A-2B77-464C-A89E-4C6925E776DC",
        "mainsnak": {
          "datatype": "commonsMedia",
          "datavalue": {
            "type": "string",
            "value": "NN (2) ferch William ap Jenkin ap Philip Arms.svg"
          },
          "hash": "7a759c7cdc62339db71807c3f342a0d543f93460",
          "property": "P94",
          "snaktype": "value"
        },
        "rank": "normal",
        "type": "statement"
      }
    ]
  },
  "descriptions": {},
  "id": "Q145899",
  "labels": {
    "cy": {
      "language": "cy",
      "value": "NN (2) ferch William ap Jenkin ap Philip"
    },
    "en": {
      "language": "en",
      "value": "NN (2) ferch William ap Jenkin ap Philip"
    }
  },
  "lastrevid": 17569408,
  "modified": "2025-09-17T14:42:18Z",
  "ns": 860,
  "pageid": 174284,
  "sitelinks": {},
  "title": "Item:Q145899",
  "type": "item"
}
