{
  "aliases": {
    "en": [
      {
        "language": "en",
        "value": "Dafydd ab Iorwerth Amaeth ap Rhys ap Maredudd"
      }
    ]
  },
  "claims": {
    "P1819": [
      {
        "id": "Q148848$70F1B5BA-363B-42AC-A46E-5E2277E7A151",
        "mainsnak": {
          "datatype": "external-id",
          "datavalue": {
            "type": "string",
            "value": "I00708497"
          },
          "hash": "4e3b11daba1ce26c1bd883601fb7cb600ec56f38",
          "property": "P1819",
          "snaktype": "value"
        },
        "rank": "normal",
        "type": "statement"
      }
    ],
    "P39": [
      {
        "id": "Q148848$698CCA6C-CEA2-4812-AB72-B87E1C162553",
        "mainsnak": {
          "datatype": "wikibase-item",
          "datavalue": {
            "type": "wikibase-entityid",
            "value": {
              "entity-type": "item",
              "id": "Q153801",
              "numeric-id": 153801
            }
          },
          "hash": "b90991d245ed2a6e8cec5d5ae903ed799cdc2705",
          "property": "P39",
          "snaktype": "value"
        },
        "rank": "normal",
        "type": "statement"
      },
      {
        "id": "Q148848$8809C26C-8196-45AB-B037-722A0E43F264",
        "mainsnak": {
          "datatype": "wikibase-item",
          "datavalue": {
            "type": "wikibase-entityid",
            "value": {
              "entity-type": "item",
              "id": "Q153802",
              "numeric-id": 153802
            }
          },
          "hash": "b9eb3a19c3f2fb9d80823c0663c5704bf3f90255",
          "property": "P39",
          "snaktype": "value"
        },
        "rank": "normal",
        "type": "statement"
      }
    ],
    "P47": [
      {
        "id": "Q148848$BCDB709A-655E-41E8-A8A4-8531B8D40331",
        "mainsnak": {
          "datatype": "wikibase-item",
          "datavalue": {
            "type": "wikibase-entityid",
            "value": {
              "entity-type": "item",
              "id": "Q144827",
              "numeric-id": 144827
            }
          },
          "hash": "897e4ea1cfb888def5cbb96d2d65b47e5c75a7b0",
          "property": "P47",
          "snaktype": "value"
        },
        "rank": "normal",
        "type": "statement"
      }
    ],
    "P55": [
      {
        "id": "Q148848$F72B8D1C-26C4-4364-8C4B-71147DBCE9BC",
        "mainsnak": {
          "datatype": "wikibase-item",
          "datavalue": {
            "type": "wikibase-entityid",
            "value": {
              "entity-type": "item",
              "id": "Q153718",
              "numeric-id": 153718
            }
          },
          "hash": "2c0169b343dfa052299eaa3878c187394e4e584c",
          "property": "P55",
          "snaktype": "value"
        },
        "rank": "normal",
        "type": "statement"
      }
    ],
    "P61": [
      {
        "id": "Q148848$C357B5FF-2FA3-4975-BCBF-38DD484016A0",
        "mainsnak": {
          "datatype": "external-id",
          "datavalue": {
            "type": "string",
            "value": "Q117307034"
          },
          "hash": "38ac70dde5a984049e5782d2c6ddc669536eb839",
          "property": "P61",
          "snaktype": "value"
        },
        "rank": "normal",
        "type": "statement"
      }
    ],
    "P94": [
      {
        "id": "Q148848$794C62C8-AB35-4303-B279-6CBB58EF3698",
        "mainsnak": {
          "datatype": "commonsMedia",
          "datavalue": {
            "type": "string",
            "value": "Dafydd ab Iorwerth Amaeth ap Rhys ap Maredudd Arms.svg"
          },
          "hash": "79532117de20e8b396cf2d0505f05cd6497d86b6",
          "property": "P94",
          "snaktype": "value"
        },
        "rank": "normal",
        "type": "statement"
      }
    ]
  },
  "descriptions": {},
  "id": "Q148848",
  "labels": {
    "en": {
      "language": "en",
      "value": "Dafydd ab Iorwerth Amaeth ap Rhys ap Maredudd"
    }
  },
  "lastrevid": 17574202,
  "modified": "2025-09-17T15:50:38Z",
  "ns": 860,
  "pageid": 177301,
  "sitelinks": {},
  "title": "Item:Q148848",
  "type": "item"
}
