{
  "aliases": {},
  "claims": {
    "P20": [
      {
        "id": "Q169369$B0067153-9E0D-A484-1ECD-172F49926D1D",
        "mainsnak": {
          "datatype": "wikibase-item",
          "datavalue": {
            "type": "wikibase-entityid",
            "value": {
              "entity-type": "item",
              "id": "Q169370",
              "numeric-id": 169370
            }
          },
          "hash": "0d2e4fea764b3ca91af534883bcd7f8f28834fea",
          "property": "P20",
          "snaktype": "value"
        },
        "rank": "normal",
        "type": "statement"
      }
    ],
    "P39": [
      {
        "id": "Q169369$D85FE79E-755A-481E-86C7-2347CFD0A588",
        "mainsnak": {
          "datatype": "wikibase-item",
          "datavalue": {
            "type": "wikibase-entityid",
            "value": {
              "entity-type": "item",
              "id": "Q153801",
              "numeric-id": 153801
            }
          },
          "hash": "b90991d245ed2a6e8cec5d5ae903ed799cdc2705",
          "property": "P39",
          "snaktype": "value"
        },
        "rank": "normal",
        "type": "statement"
      },
      {
        "id": "Q169369$A50FEEA4-3C45-4CC9-BFD6-8C742EAA3FAC",
        "mainsnak": {
          "datatype": "wikibase-item",
          "datavalue": {
            "type": "wikibase-entityid",
            "value": {
              "entity-type": "item",
              "id": "Q153802",
              "numeric-id": 153802
            }
          },
          "hash": "b9eb3a19c3f2fb9d80823c0663c5704bf3f90255",
          "property": "P39",
          "snaktype": "value"
        },
        "rank": "normal",
        "type": "statement"
      }
    ],
    "P42": [
      {
        "id": "Q169369$DAD58C4D-C93F-5CE4-D719-92BB1C865C7C",
        "mainsnak": {
          "datatype": "wikibase-item",
          "datavalue": {
            "type": "wikibase-entityid",
            "value": {
              "entity-type": "item",
              "id": "Q169136",
              "numeric-id": 169136
            }
          },
          "hash": "52d5117a39be122462b1ee2ac0c958747e47592d",
          "property": "P42",
          "snaktype": "value"
        },
        "rank": "normal",
        "type": "statement"
      }
    ],
    "P55": [
      {
        "id": "Q169369$28A89B9B-CB22-51A1-1C39-A1A40C9E3C68",
        "mainsnak": {
          "datatype": "wikibase-item",
          "datavalue": {
            "type": "wikibase-entityid",
            "value": {
              "entity-type": "item",
              "id": "Q153719",
              "numeric-id": 153719
            }
          },
          "hash": "b13089fc8bec4016f0842734a590d288c2e6ef4b",
          "property": "P55",
          "snaktype": "value"
        },
        "rank": "normal",
        "type": "statement"
      }
    ],
    "P62": [
      {
        "id": "Q169369$DFF476E7-4330-D5CA-7E70-781D3A94CABE",
        "mainsnak": {
          "datatype": "external-id",
          "datavalue": {
            "type": "string",
            "value": "6000000019344610001"
          },
          "hash": "fa3ffc1b1bd252a7d34f199126ea0360ad28cdcf",
          "property": "P62",
          "snaktype": "value"
        },
        "rank": "normal",
        "type": "statement"
      }
    ],
    "P94": [
      {
        "id": "Q169369$9C0D5DA4-F2A9-4501-820A-52F422102A44",
        "mainsnak": {
          "datatype": "commonsMedia",
          "datavalue": {
            "type": "string",
            "value": "sarasvati river Arms.svg"
          },
          "hash": "e7388912b4ff76407d04efd12c586528a74c6b33",
          "property": "P94",
          "snaktype": "value"
        },
        "rank": "normal",
        "type": "statement"
      }
    ]
  },
  "descriptions": {},
  "id": "Q169369",
  "labels": {
    "en": {
      "language": "en",
      "value": "sarasvati river"
    }
  },
  "lastrevid": 17600034,
  "modified": "2025-09-17T21:39:59Z",
  "ns": 860,
  "pageid": 212534,
  "sitelinks": {},
  "title": "Item:Q169369",
  "type": "item"
}
