{
  "aliases": {
    "en": [
      {
        "language": "en",
        "value": "Yelu Yaoshinu //"
      }
    ]
  },
  "claims": {
    "P39": [
      {
        "id": "Q49302$FF3EDF31-C51B-4EC5-8835-11452F73FE27",
        "mainsnak": {
          "datatype": "wikibase-item",
          "datavalue": {
            "type": "wikibase-entityid",
            "value": {
              "entity-type": "item",
              "id": "Q153801",
              "numeric-id": 153801
            }
          },
          "hash": "b90991d245ed2a6e8cec5d5ae903ed799cdc2705",
          "property": "P39",
          "snaktype": "value"
        },
        "rank": "normal",
        "type": "statement"
      },
      {
        "id": "Q49302$13EA9E60-7BD8-4B66-83E3-DBB684A05307",
        "mainsnak": {
          "datatype": "wikibase-item",
          "datavalue": {
            "type": "wikibase-entityid",
            "value": {
              "entity-type": "item",
              "id": "Q153802",
              "numeric-id": 153802
            }
          },
          "hash": "b9eb3a19c3f2fb9d80823c0663c5704bf3f90255",
          "property": "P39",
          "snaktype": "value"
        },
        "rank": "normal",
        "type": "statement"
      }
    ],
    "P47": [
      {
        "id": "Q49302$3ED4ACA5-7098-4333-B823-D3F3569A7364",
        "mainsnak": {
          "datatype": "wikibase-item",
          "datavalue": {
            "type": "wikibase-entityid",
            "value": {
              "entity-type": "item",
              "id": "Q45853",
              "numeric-id": 45853
            }
          },
          "hash": "008fed8d03deb0b755a139891700ec25f66bbce2",
          "property": "P47",
          "snaktype": "value"
        },
        "rank": "normal",
        "type": "statement"
      }
    ],
    "P55": [
      {
        "id": "Q49302$49967AA0-A689-4B16-B041-10056F45AB09",
        "mainsnak": {
          "datatype": "wikibase-item",
          "datavalue": {
            "type": "wikibase-entityid",
            "value": {
              "entity-type": "item",
              "id": "Q153718",
              "numeric-id": 153718
            }
          },
          "hash": "2c0169b343dfa052299eaa3878c187394e4e584c",
          "property": "P55",
          "snaktype": "value"
        },
        "rank": "normal",
        "type": "statement"
      }
    ],
    "P57": [
      {
        "id": "Q49302$C0FB5645-1BC0-4F87-B573-9D99C76F1499",
        "mainsnak": {
          "datatype": "time",
          "datavalue": {
            "type": "time",
            "value": {
              "after": 0,
              "before": 0,
              "calendarmodel": "http://www.wikidata.org/entity/Q1985727",
              "precision": 11,
              "time": "+0981-01-01T00:00:00Z",
              "timezone": 0
            }
          },
          "hash": "e84d8b73c13e615138ff7306fd5e4504e3f10d02",
          "property": "P57",
          "snaktype": "value"
        },
        "rank": "normal",
        "type": "statement"
      }
    ],
    "P61": [
      {
        "id": "Q49302$CF021E6D-6D9C-4825-A02F-E325EB28E16D",
        "mainsnak": {
          "datatype": "external-id",
          "datavalue": {
            "type": "string",
            "value": "Q15953310"
          },
          "hash": "16094b0a090171af8ba96da715302c70027a1fb3",
          "property": "P61",
          "snaktype": "value"
        },
        "rank": "normal",
        "type": "statement"
      }
    ],
    "P62": [
      {
        "id": "Q49302$76789379-E376-4D3E-A463-708ED7AB41CD",
        "mainsnak": {
          "datatype": "external-id",
          "datavalue": {
            "type": "string",
            "value": "6000000074792072859"
          },
          "hash": "31b9db621b40bfc064a7e9ab26b6a3c787416b97",
          "property": "P62",
          "snaktype": "value"
        },
        "rank": "normal",
        "type": "statement"
      }
    ],
    "P94": [
      {
        "id": "Q49302$DF158169-9610-44FF-B18E-7816A1F0136A",
        "mainsnak": {
          "datatype": "commonsMedia",
          "datavalue": {
            "type": "string",
            "value": "Yelu Yaoshinu Arms.svg"
          },
          "hash": "d162ac99bfad53c48a3796fdbb6824c20e205093",
          "property": "P94",
          "snaktype": "value"
        },
        "rank": "normal",
        "type": "statement"
      }
    ]
  },
  "descriptions": {
    "en": {
      "language": "en",
      "value": "Chinese prince"
    },
    "nl": {
      "language": "nl",
      "value": "kroonprins uit Liao-dynastie"
    },
    "ru": {
      "language": "ru",
      "value": "китайский принц"
    }
  },
  "id": "Q49302",
  "labels": {
    "ast": {
      "language": "ast",
      "value": "Yelu Yaoshinu"
    },
    "en": {
      "language": "en",
      "value": "Yelu Yaoshinu"
    },
    "es": {
      "language": "es",
      "value": "Yelu Yaoshinu"
    },
    "lzh": {
      "language": "lzh",
      "value": "耶律藥師奴"
    },
    "nl": {
      "language": "nl",
      "value": "Yelv Yaoshinu"
    },
    "ru": {
      "language": "ru",
      "value": "Елюй Яошину"
    },
    "sq": {
      "language": "sq",
      "value": "Yelv Yaoshinu"
    },
    "zh": {
      "language": "zh",
      "value": "耶律药师奴"
    },
    "zh-hans": {
      "language": "zh-hans",
      "value": "耶律药师奴"
    },
    "zh-hant": {
      "language": "zh-hant",
      "value": "耶律藥師奴"
    }
  },
  "lastrevid": 17455030,
  "modified": "2025-09-16T11:06:18Z",
  "ns": 860,
  "pageid": 64645,
  "sitelinks": {},
  "title": "Item:Q49302",
  "type": "item"
}
