{
  "aliases": {},
  "claims": {
    "P39": [
      {
        "id": "Q56267$E13681C6-1442-4C4D-899A-99C252050C61",
        "mainsnak": {
          "datatype": "wikibase-item",
          "datavalue": {
            "type": "wikibase-entityid",
            "value": {
              "entity-type": "item",
              "id": "Q153801",
              "numeric-id": 153801
            }
          },
          "hash": "b90991d245ed2a6e8cec5d5ae903ed799cdc2705",
          "property": "P39",
          "snaktype": "value"
        },
        "rank": "normal",
        "type": "statement"
      },
      {
        "id": "Q56267$6007FBE1-8A5E-400E-A6F9-1BBECDACEDF3",
        "mainsnak": {
          "datatype": "wikibase-item",
          "datavalue": {
            "type": "wikibase-entityid",
            "value": {
              "entity-type": "item",
              "id": "Q153802",
              "numeric-id": 153802
            }
          },
          "hash": "b9eb3a19c3f2fb9d80823c0663c5704bf3f90255",
          "property": "P39",
          "snaktype": "value"
        },
        "rank": "normal",
        "type": "statement"
      }
    ],
    "P47": [
      {
        "id": "Q56267$9E7CAF6A-5C5A-4550-ADEB-DB53667D10D8",
        "mainsnak": {
          "datatype": "wikibase-item",
          "datavalue": {
            "type": "wikibase-entityid",
            "value": {
              "entity-type": "item",
              "id": "Q56066",
              "numeric-id": 56066
            }
          },
          "hash": "3b93de7df62d43e941074624cf9d5992c06876c0",
          "property": "P47",
          "snaktype": "value"
        },
        "rank": "normal",
        "type": "statement"
      }
    ],
    "P5": [
      {
        "id": "Q56267$E8B1DB63-5096-4104-B1A8-9C0D491E4DE7",
        "mainsnak": {
          "datatype": "monolingualtext",
          "datavalue": {
            "type": "monolingualtext",
            "value": {
              "language": "en",
              "text": "林升 /第16世长林衍派/"
            }
          },
          "hash": "7f69ec49490fa13c224f1ceaeb82457d1b6f0b60",
          "property": "P5",
          "snaktype": "value"
        },
        "rank": "normal",
        "type": "statement"
      }
    ],
    "P55": [
      {
        "id": "Q56267$17BE8E79-4961-4904-B62C-B920E4A1F204",
        "mainsnak": {
          "datatype": "wikibase-item",
          "datavalue": {
            "type": "wikibase-entityid",
            "value": {
              "entity-type": "item",
              "id": "Q153718",
              "numeric-id": 153718
            }
          },
          "hash": "2c0169b343dfa052299eaa3878c187394e4e584c",
          "property": "P55",
          "snaktype": "value"
        },
        "rank": "normal",
        "type": "statement"
      }
    ],
    "P94": [
      {
        "id": "Q56267$3A76E398-C07F-460D-9DC5-717FCA0379A7",
        "mainsnak": {
          "datatype": "commonsMedia",
          "datavalue": {
            "type": "string",
            "value": "  16 Arms.svg"
          },
          "hash": "4046d1ead21071790fb2598b2136f225d3352005",
          "property": "P94",
          "snaktype": "value"
        },
        "rank": "normal",
        "type": "statement"
      }
    ]
  },
  "descriptions": {},
  "id": "Q56267",
  "labels": {
    "en": {
      "language": "en",
      "value": "  16"
    },
    "zh": {
      "language": "zh",
      "value": "林升  第16世长林衍派"
    }
  },
  "lastrevid": 17464656,
  "modified": "2025-09-16T13:28:58Z",
  "ns": 860,
  "pageid": 71098,
  "sitelinks": {},
  "title": "Item:Q56267",
  "type": "item"
}
