{
  "aliases": {},
  "claims": {
    "P20": [
      {
        "id": "Q70193$AD0589CE-0670-472F-B6ED-A90B9A7F6FFF",
        "mainsnak": {
          "datatype": "wikibase-item",
          "datavalue": {
            "type": "wikibase-entityid",
            "value": {
              "entity-type": "item",
              "id": "Q70196",
              "numeric-id": 70196
            }
          },
          "hash": "c6788c788d7b54fd027b09ad42caadd5d7eb06b8",
          "property": "P20",
          "snaktype": "value"
        },
        "rank": "normal",
        "type": "statement"
      }
    ],
    "P39": [
      {
        "id": "Q70193$E0CF3046-D0B7-498A-81A4-DCD3F881BB1F",
        "mainsnak": {
          "datatype": "wikibase-item",
          "datavalue": {
            "type": "wikibase-entityid",
            "value": {
              "entity-type": "item",
              "id": "Q153801",
              "numeric-id": 153801
            }
          },
          "hash": "b90991d245ed2a6e8cec5d5ae903ed799cdc2705",
          "property": "P39",
          "snaktype": "value"
        },
        "rank": "normal",
        "type": "statement"
      },
      {
        "id": "Q70193$77AF6AD4-B799-4CF6-9E0E-4B3DACD818E0",
        "mainsnak": {
          "datatype": "wikibase-item",
          "datavalue": {
            "type": "wikibase-entityid",
            "value": {
              "entity-type": "item",
              "id": "Q153802",
              "numeric-id": 153802
            }
          },
          "hash": "b9eb3a19c3f2fb9d80823c0663c5704bf3f90255",
          "property": "P39",
          "snaktype": "value"
        },
        "rank": "normal",
        "type": "statement"
      }
    ],
    "P47": [
      {
        "id": "Q70193$21CD5B64-8405-4891-A712-E091F02956DE",
        "mainsnak": {
          "datatype": "wikibase-item",
          "datavalue": {
            "type": "wikibase-entityid",
            "value": {
              "entity-type": "item",
              "id": "Q70190",
              "numeric-id": 70190
            }
          },
          "hash": "9a157eb7dbd2103e3bd492405113745b3dae03a6",
          "property": "P47",
          "snaktype": "value"
        },
        "rank": "normal",
        "type": "statement"
      }
    ],
    "P5": [
      {
        "id": "Q70193$ABF24714-9BD2-4D0E-9D23-024DD5165EFB",
        "mainsnak": {
          "datatype": "monolingualtext",
          "datavalue": {
            "type": "monolingualtext",
            "value": {
              "language": "en",
              "text": "Takashi (隆) /Jī (姬), King of Yayoi/"
            }
          },
          "hash": "0a6ca437900dba1a38b8f5a8f7ec9b32f1cd2ef7",
          "property": "P5",
          "snaktype": "value"
        },
        "rank": "normal",
        "type": "statement"
      }
    ],
    "P55": [
      {
        "id": "Q70193$1A508494-B39D-44E3-9083-B693914D1770",
        "mainsnak": {
          "datatype": "wikibase-item",
          "datavalue": {
            "type": "wikibase-entityid",
            "value": {
              "entity-type": "item",
              "id": "Q153718",
              "numeric-id": 153718
            }
          },
          "hash": "2c0169b343dfa052299eaa3878c187394e4e584c",
          "property": "P55",
          "snaktype": "value"
        },
        "rank": "normal",
        "type": "statement"
      }
    ],
    "P94": [
      {
        "id": "Q70193$76E3EB32-D6E7-4A30-99FA-EBDD1CAA8E53",
        "mainsnak": {
          "datatype": "commonsMedia",
          "datavalue": {
            "type": "string",
            "value": "22 Arms.svg"
          },
          "hash": "4c23a272725b7e7d54d4675b2b1858473079499e",
          "property": "P94",
          "snaktype": "value"
        },
        "rank": "normal",
        "type": "statement"
      }
    ]
  },
  "descriptions": {},
  "id": "Q70193",
  "labels": {
    "en": {
      "language": "en",
      "value": "22"
    },
    "es": {
      "language": "es",
      "value": "Takashi Jī, King of Yayoi"
    }
  },
  "lastrevid": 17481946,
  "modified": "2025-09-16T17:45:25Z",
  "ns": 860,
  "pageid": 85024,
  "sitelinks": {},
  "title": "Item:Q70193",
  "type": "item"
}
